Metadata-Version: 1.1
Name: django-sql
Version: 1.0
Summary: A simple app for executing SQL queries in Django admin panel
Home-page: https://github.com/luminousmen/django-sql
Author: Kirill Bobrov
Author-email: miaplanedo@gmail.com
License: MIT License
Platform: UNKNOWN
Classifier: Framework :: Django
Classifier: Intended Audience :: Developers
Classifier: License :: OSI Approved :: BSD License
Classifier: Operating System :: OS Independent
Classifier: Programming Language :: Python
Classifier: Programming Language :: Python :: 2
Classifier: Programming Language :: Python :: 3
Classifier: Programming Language :: Python :: 3.4
Classifier: Programming Language :: Python :: 3.5
Classifier: Topic :: Internet :: WWW/HTTP
Classifier: Topic :: Internet :: WWW/HTTP :: Dynamic Content
